Metadata-Version: 2.1
Name: gvicencotti_image_processor
Version: 0.0.1
Summary: Image Processing Package using skimage
Home-page: https://github.com/gvicencotti/image-processing-package
Author: Gustavo
Author-email: gustavovicencotti@gmail.com
Requires-Python: >=3.8
Requires-Dist: matplotlib
Requires-Dist: numpy
Requires-Dist: scikit-image >=0.16.1
